vldb_toolkits/__init__.py
vldb_toolkits/__main__.py
vldb_toolkits/_post_install.py
vldb_toolkits/cli.py
vldb_toolkits/config.py
vldb_toolkits/downloader.py
vldb_toolkits-0.2.0.data/data/vldb_toolkits.pth
vldb_toolkits-0.2.0.dist-info/licenses/LICENSE
vldb_toolkits-0.2.0.dist-info/METADATA
vldb_toolkits-0.2.0.dist-info/WHEEL
vldb_toolkits-0.2.0.dist-info/entry_points.txt
vldb_toolkits-0.2.0.dist-info/top_level.txt
vldb_toolkits-0.2.0.dist-info/RECORD
