Metadata-Version: 2.4
Name: vldb-toolkits
Version: 0.2.0
Summary: Paper Management Platform for VLDB - Python wrapper for desktop application
Author-email: Silan Hu <silan.hu@u.nus.edu>
License: MIT
Project-URL: Homepage, https://github.com/Qingbolan/VLDB-Toolkits
Project-URL: Repository, https://github.com/Qingbolan/VLDB-Toolkits
Project-URL: Issues, https://github.com/Qingbolan/VLDB-Toolkits/issues
Keywords: vldb,paper-management,academic,research,desktop-application
Classifier: Development Status :: 3 - Alpha
Classifier: Intended Audience :: Science/Research
Classifier: Intended Audience :: Education
Classifier: Topic :: Scientific/Engineering
Classifier: Topic :: Office/Business
Classifier: License :: OSI Approved :: MIT License
Classifier: Programming Language :: Python :: 3
Classifier: Programming Language :: Python :: 3.8
Classifier: Programming Language :: Python :: 3.9
Classifier: Programming Language :: Python :: 3.10
Classifier: Programming Language :: Python :: 3.11
Classifier: Programming Language :: Python :: 3.12
Classifier: Operating System :: OS Independent
Requires-Python: >=3.8
License-File: LICENSE
Dynamic: license-file
